mlconjug3/BUILD
mlconjug3/__init__.py
mlconjug3/__init__.pyi
mlconjug3/cli.py
mlconjug3/cli.pyi
mlconjug3/mlconjug.py
mlconjug3/mlconjug.pyi
mlconjug3/py.typed
mlconjug3/PyVerbiste/BUILD
mlconjug3/PyVerbiste/PyVerbiste.py
mlconjug3/PyVerbiste/PyVerbiste.pyi
mlconjug3/PyVerbiste/__init__.py
mlconjug3/config/config.yaml
mlconjug3/conjug_manager/BUILD
mlconjug3/conjug_manager/__init__.py
mlconjug3/conjug_manager/conjug_manager.py
mlconjug3/conjug_manager/conjug_manager.pyi
mlconjug3/constants/BUILD
mlconjug3/constants/__init__.py
mlconjug3/constants/constants.py
mlconjug3/constants/constants.pyi
mlconjug3/data/conjug_manager/conjugation-en.json
mlconjug3/data/conjug_manager/conjugation-en.xml
mlconjug3/data/conjug_manager/conjugation-en.xml.pkl
mlconjug3/data/conjug_manager/conjugation-es.json
mlconjug3/data/conjug_manager/conjugation-es.xml
mlconjug3/data/conjug_manager/conjugation-es.xml.pkl
mlconjug3/data/conjug_manager/conjugation-fr.json
mlconjug3/data/conjug_manager/conjugation-fr.xml
mlconjug3/data/conjug_manager/conjugation-fr.xml.pkl
mlconjug3/data/conjug_manager/conjugation-it.json
mlconjug3/data/conjug_manager/conjugation-it.xml
mlconjug3/data/conjug_manager/conjugation-it.xml.pkl
mlconjug3/data/conjug_manager/conjugation-pt.json
mlconjug3/data/conjug_manager/conjugation-pt.xml
mlconjug3/data/conjug_manager/conjugation-pt.xml.pkl
mlconjug3/data/conjug_manager/conjugation-ro.json
mlconjug3/data/conjug_manager/conjugation-ro.xml
mlconjug3/data/conjug_manager/conjugation-ro.xml.pkl
mlconjug3/data/conjug_manager/verbiste-es-en-it-pt-ro.zip
mlconjug3/data/conjug_manager/verbs-en.json
mlconjug3/data/conjug_manager/verbs-en.xml
mlconjug3/data/conjug_manager/verbs-en.xml.pkl
mlconjug3/data/conjug_manager/verbs-es.json
mlconjug3/data/conjug_manager/verbs-es.xml
mlconjug3/data/conjug_manager/verbs-es.xml.pkl
mlconjug3/data/conjug_manager/verbs-fr.json
mlconjug3/data/conjug_manager/verbs-fr.xml
mlconjug3/data/conjug_manager/verbs-fr.xml.pkl
mlconjug3-3.11.0.dist-info/AUTHORS.rst
mlconjug3-3.11.0.dist-info/LICENSE
mlconjug3-3.11.0.dist-info/METADATA
mlconjug3-3.11.0.dist-info/WHEEL
mlconjug3-3.11.0.dist-info/entry_points.txt
mlconjug3-3.11.0.dist-info/top_level.txt
mlconjug3-3.11.0.dist-info/RECORD
