Metadata-Version: 2.1
Name: mlconjug3
Version: 3.11.0
Summary: A Python library to conjugate French, English, Spanish, Italian, Portuguese and Romanian verbs using Machine Learning techniques.
Home-page: https://github.com/Ars-Linguistica/mlconjug3
Author: Ars-Linguistica
Author-email: diao.sekou.nlp@gmail.com
License: MIT license
Keywords: mlconjug3 conjugate conjugator conjugation conjugaison conjugación coniugazione conjugação conjugare verbs verbes verbos ML machine-learning NLP linguistics linguistique linguistica conjug_manager sklearnscikit-learn
Classifier: Development Status :: 5 - Production/Stable
Classifier: Topic :: Software Development :: Libraries :: Python Modules
Classifier: Topic :: Education
Classifier: Topic :: Scientific/Engineering :: Artificial Intelligence
Classifier: Topic :: Utilities
Classifier: Intended Audience :: Developers
Classifier: Intended Audience :: End Users/Desktop
Classifier: Intended Audience :: Education
Classifier: Intended Audience :: Science/Research
Classifier: License :: OSI Approved :: MIT License
Classifier: Natural Language :: English
Classifier: Natural Language :: French
Classifier: Natural Language :: Spanish
Classifier: Natural Language :: Italian
Classifier: Natural Language :: Portuguese
Classifier: Natural Language :: Romanian
Classifier: Operating System :: OS Independent
Classifier: Programming Language :: Python :: 3
Classifier: Programming Language :: Python :: 3.8
Classifier: Programming Language :: Python :: 3.9
Classifier: Programming Language :: Python :: 3.10
Classifier: Programming Language :: Python :: 3.11
License-File: LICENSE
License-File: AUTHORS.rst
